{
  "id": "3458764655397505966",
  "status": "Created",
  "title": "slice: Create Account",
  "context": "Registration",
  "sliceType": "STATE_CHANGE",
  "commands": [
    {
      "id": "3458764655390776063",
      "tags": [],
      "elementContext": "INTERNAL",
      "modelContext": "Registration",
      "context": "INTERNAL",
      "slice": "slice: Create Account",
      "title": "Create Account",
      "fields": [
        {
          "name": "user_id",
          "type": "UUID",
          "subfields": [],
          "cardinality": "Single",
          "idAttribute": false
        },
        {
          "name": "email",
          "type": "String",
          "subfields": [],
          "cardinality": "Single",
          "idAttribute": false
        },
        {
          "name": "name",
          "type": "String",
          "subfields": [],
          "cardinality": "Single",
          "idAttribute": false
        }
      ],
      "type": "COMMAND",
      "description": "",
      "aggregate": "Registration",
      "aggregateDependencies": [
        "Registration"
      ],
      "dependencies": [
        {
          "id": "3458764655390014478",
          "type": "OUTBOUND",
          "title": "Account created",
          "elementType": "EVENT"
        },
        {
          "id": "3458764655390559910",
          "type": "INBOUND",
          "title": "screen",
          "elementType": "SCREEN"
        }
      ],
      "createsAggregate": false,
      "triggers": [],
      "sketched": false,
      "prototype": {
        "activeByDefault": false
      }
    }
  ],
  "events": [
    {
      "id": "3458764655390014478",
      "tags": [],
      "elementContext": "INTERNAL",
      "modelContext": "Registration",
      "context": "INTERNAL",
      "slice": "slice: Create Account",
      "title": "Account created",
      "fields": [
        {
          "name": "user id",
          "type": "UUID",
          "subfields": [],
          "cardinality": "Single",
          "idAttribute": true
        },
        {
          "name": "email",
          "type": "String",
          "subfields": [],
          "cardinality": "Single",
          "idAttribute": false
        },
        {
          "name": "name",
          "type": "String",
          "subfields": [],
          "cardinality": "Single",
          "idAttribute": false
        }
      ],
      "type": "EVENT",
      "description": "",
      "aggregate": "Registration",
      "aggregateDependencies": [
        "Registration"
      ],
      "dependencies": [
        {
          "id": "3458764655392353436",
          "type": "OUTBOUND",
          "title": "Confirmed Accounts",
          "elementType": "READMODEL"
        },
        {
          "id": "3458764655391010052",
          "type": "OUTBOUND",
          "title": "Confirmation Mails to send TODO",
          "elementType": "READMODEL"
        },
        {
          "id": "3458764655390776063",
          "type": "INBOUND",
          "title": "Create Account",
          "elementType": "COMMAND"
        }
      ],
      "createsAggregate": false,
      "triggers": [],
      "sketched": false,
      "prototype": {
        "activeByDefault": false
      }
    }
  ],
  "readmodels": [],
  "screens": [
    {
      "id": "3458764655390559910",
      "tags": [],
      "groupId": "3458764655390559914",
      "elementContext": "INTERNAL",
      "modelContext": "Registration",
      "context": "INTERNAL",
      "slice": "slice: Create Account",
      "title": "screen",
      "fields": [
        {
          "name": "email",
          "type": "String",
          "subfields": [],
          "cardinality": "Single",
          "idAttribute": false
        },
        {
          "name": "user_id",
          "type": "UUID",
          "subfields": [],
          "cardinality": "Single",
          "idAttribute": false
        },
        {
          "name": "name",
          "type": "String",
          "subfields": [],
          "cardinality": "Single",
          "idAttribute": false
        }
      ],
      "type": "SCREEN",
      "description": "",
      "aggregate": "Registration",
      "aggregateDependencies": [
        "Registration"
      ],
      "dependencies": [
        {
          "id": "3458764655390776063",
          "type": "OUTBOUND",
          "title": "Create Account",
          "elementType": "COMMAND"
        }
      ],
      "createsAggregate": false,
      "triggers": [],
      "sketched": true,
      "prototype": {
        "activeByDefault": false
      }
    }
  ],
  "screenImages": [],
  "screenLayouts": [],
  "processors": [],
  "tables": [],
  "specifications": [
    {
      "vertical": false,
      "id": "3458764655610377233",
      "sliceName": "slice: Create Account",
      "title": "spec: Create Account - scenario",
      "given": [
        {
          "title": "Account created",
          "tags": [],
          "examples": [],
          "id": "3458764655610377242",
          "index": 0,
          "specRow": -1,
          "type": "SPEC_EVENT",
          "fields": [
            {
              "name": "user id",
              "type": "UUID",
              "subfields": [],
              "cardinality": "Single",
              "idAttribute": true,
              "example": ""
            },
            {
              "name": "email",
              "type": "String",
              "subfields": [],
              "cardinality": "Single",
              "example": "martin@nebulit.de"
            },
            {
              "name": "name",
              "type": "String",
              "subfields": [],
              "cardinality": "Single",
              "example": ""
            }
          ],
          "linkedId": "3458764655390014478"
        }
      ],
      "when": [
        {
          "title": "Create Account",
          "tags": [],
          "examples": [],
          "id": "3458764655610377238",
          "index": 0,
          "specRow": -1,
          "type": "SPEC_COMMAND",
          "fields": [
            {
              "name": "user_id",
              "type": "UUID",
              "subfields": [],
              "cardinality": "Single",
              "example": ""
            },
            {
              "name": "email",
              "type": "String",
              "subfields": [],
              "cardinality": "Single",
              "example": "martin@nebulit.de"
            },
            {
              "name": "name",
              "type": "String",
              "subfields": [],
              "cardinality": "Single",
              "example": ""
            }
          ],
          "linkedId": "3458764655390776063"
        }
      ],
      "then": [
        {
          "title": "emails can only be registered once",
          "tags": [],
          "id": "3458764655610377240",
          "index": 0,
          "specRow": -1,
          "type": "SPEC_ERROR",
          "fields": []
        }
      ],
      "comments": [],
      "linkedId": "3458764655397505966"
    }
  ],
  "actors": [],
  "aggregates": [
    "Registration"
  ]
}