{
  "id": "3458764643953804976",
  "status": "Done",
  "index": 109,
  "title": "slice: case Attach Authority",
  "context": "Case Management",
  "sliceType": "STATE_CHANGE",
  "commands": [
    {
      "id": "3458764591891053432",
      "tags": [],
      "domain": "",
      "elementContext": "INTERNAL",
      "modelContext": "Case Management",
      "context": "INTERNAL",
      "slice": "slice: case Attach Authority",
      "title": "Case Attach Authority",
      "fields": [
        {
          "name": "aggregateId",
          "type": "UUID",
          "cardinality": "Single",
          "idAttribute": false
        },
        {
          "name": "responsible",
          "type": "Boolean",
          "generated": true,
          "cardinality": "Single",
          "idAttribute": false
        },
        {
          "name": "authorityId",
          "type": "UUID",
          "mapping": "aggregateId",
          "cardinality": "Single",
          "idAttribute": false
        },
        {
          "name": "jucidicalInstanceName",
          "type": "String",
          "cardinality": "Single",
          "idAttribute": false
        },
        {
          "name": "caseNumber",
          "type": "String",
          "generated": true,
          "cardinality": "Single",
          "idAttribute": false
        },
        {
          "name": "lawfirmId",
          "type": "UUID",
          "cardinality": "Single",
          "idAttribute": false
        }
      ],
      "type": "COMMAND",
      "description": "",
      "aggregate": "Case",
      "aggregateDependencies": [
        "Case"
      ],
      "dependencies": [
        {
          "id": "3458764591892917657",
          "type": "OUTBOUND",
          "title": "Case Authority Attached",
          "elementType": "EVENT"
        },
        {
          "id": "3458764590947667874",
          "type": "INBOUND",
          "title": "screen",
          "elementType": "SCREEN"
        }
      ],
      "createsAggregate": false,
      "triggers": [],
      "sketched": false,
      "prototype": {
        "activeByDefault": false
      }
    }
  ],
  "events": [
    {
      "id": "3458764593410926547",
      "tags": [],
      "domain": "",
      "elementContext": "INTERNAL",
      "modelContext": "Case Management",
      "context": "INTERNAL",
      "slice": "slice: case Attach Authority",
      "title": "Case Opponent Deleted",
      "fields": [
        {
          "name": "aggregateId",
          "type": "UUID",
          "example": "",
          "mapping": "",
          "cardinality": "Single",
          "idAttribute": false
        },
        {
          "name": "personId",
          "type": "UUID",
          "example": "",
          "mapping": "",
          "cardinality": "Single",
          "idAttribute": false
        }
      ],
      "type": "EVENT",
      "description": "",
      "aggregate": "Case",
      "aggregateDependencies": [
        "Case"
      ],
      "dependencies": [
        {
          "id": "3458764593410926545",
          "type": "INBOUND",
          "title": "Delete Case Opponent",
          "elementType": "COMMAND"
        }
      ],
      "apiEndpoint": "",
      "createsAggregate": false,
      "triggers": [],
      "sketched": false,
      "prototype": {
        "activeByDefault": false
      }
    },
    {
      "id": "3458764591892917657",
      "tags": [],
      "domain": "",
      "elementContext": "INTERNAL",
      "modelContext": "Case Management",
      "context": "INTERNAL",
      "slice": "slice: case Attach Authority",
      "title": "Case Authority Attached",
      "fields": [
        {
          "name": "aggregateId",
          "type": "UUID",
          "cardinality": "Single",
          "idAttribute": false
        },
        {
          "name": "authorityId",
          "type": "UUID",
          "cardinality": "Single",
          "idAttribute": false
        },
        {
          "name": "responsible",
          "type": "Boolean",
          "cardinality": "Single",
          "idAttribute": false
        },
        {
          "name": "jucidicalInstanceName",
          "type": "String",
          "cardinality": "Single",
          "idAttribute": false
        },
        {
          "name": "caseNumber",
          "type": "String",
          "cardinality": "Single",
          "idAttribute": false
        },
        {
          "name": "lawfirmId",
          "type": "UUID",
          "cardinality": "Single",
          "idAttribute": false
        }
      ],
      "type": "EVENT",
      "description": "",
      "aggregate": "Case",
      "aggregateDependencies": [
        "Case"
      ],
      "dependencies": [
        {
          "id": "3458764654181615533",
          "type": "OUTBOUND",
          "title": "Case Overview Items",
          "elementType": "READMODEL"
        },
        {
          "id": "3458764592107985245",
          "type": "OUTBOUND",
          "title": "Case Authority Attachements",
          "elementType": "READMODEL"
        },
        {
          "id": "3458764591891053432",
          "type": "INBOUND",
          "title": "Case Attach Authority",
          "elementType": "COMMAND"
        }
      ],
      "createsAggregate": false,
      "triggers": [],
      "sketched": false,
      "prototype": {
        "activeByDefault": false
      }
    }
  ],
  "readmodels": [],
  "screens": [
    {
      "id": "3458764590947667874",
      "tags": [],
      "domain": "",
      "elementContext": "INTERNAL",
      "modelContext": "Case Management",
      "context": "INTERNAL",
      "slice": "slice: case Attach Authority",
      "title": "screen",
      "fields": [
        {
          "name": "aggregateId",
          "type": "UUID",
          "generated": true,
          "subfields": [],
          "cardinality": "Single",
          "idAttribute": false
        },
        {
          "name": "responsible",
          "type": "Boolean",
          "generated": true,
          "subfields": [],
          "cardinality": "Single",
          "idAttribute": false
        },
        {
          "name": "authorityId",
          "type": "String",
          "mapping": "id",
          "subfields": [],
          "cardinality": "Single",
          "idAttribute": false
        },
        {
          "name": "jucidicalInstanceName",
          "type": "String",
          "mapping": "name",
          "subfields": [],
          "cardinality": "Single",
          "idAttribute": false
        },
        {
          "name": "caseNumber",
          "type": "String",
          "generated": true,
          "subfields": [],
          "cardinality": "Single",
          "idAttribute": false
        },
        {
          "name": "lawfirmId",
          "type": "UUID",
          "generated": true,
          "subfields": [],
          "cardinality": "Single",
          "idAttribute": false
        }
      ],
      "type": "SCREEN",
      "description": "",
      "aggregate": "Case",
      "aggregateDependencies": [
        "Case"
      ],
      "dependencies": [
        {
          "id": "3458764591891053432",
          "type": "OUTBOUND",
          "title": "Case Attach Authority",
          "elementType": "COMMAND"
        }
      ],
      "createsAggregate": false,
      "triggers": [],
      "sketched": false,
      "prototype": {
        "activeByDefault": false
      }
    }
  ],
  "screenImages": [],
  "screenLayouts": [],
  "processors": [],
  "tables": [],
  "specifications": [],
  "actors": [
    {
      "name": "Lawyer"
    }
  ],
  "aggregates": [
    "Case"
  ]
}